src/__init__.py
src/main.py
src/server.py
src/services/__init__.py
src/services/client.py
src/services/config.py
src/tools/__init__.py
src/tools/copilot_tool.py
copilot_mcp_server-0.1.0.dist-info/METADATA
copilot_mcp_server-0.1.0.dist-info/WHEEL
copilot_mcp_server-0.1.0.dist-info/entry_points.txt
copilot_mcp_server-0.1.0.dist-info/top_level.txt
copilot_mcp_server-0.1.0.dist-info/RECORD
