Metadata-Version: 2.4
Name: copilot-mcp-server
Version: 0.1.0
Summary: MCP server for copilots with tool integrations
Author-email: Aditya Shelar <adityashe2004@karini.ai>
License: MIT
Project-URL: Homepage, https://github.com/Aditya285-S
Project-URL: Repository, https://github.com/Aditya285-S/copilot-mcp-server
Project-URL: Documentation, https://github.com/Aditya285-S/copilot-mcp-server#readme
Keywords: mcp,ai,model-context-protocol,copilot
Classifier: Development Status :: 3 - Alpha
Classifier: Intended Audience :: Developers
Classifier: License :: OSI Approved :: MIT License
Classifier: Programming Language :: Python :: 3.10
Classifier: Programming Language :: Python :: 3.11
Classifier: Programming Language :: Python :: 3.12
Classifier: Topic :: Software Development :: Libraries :: Python Modules
Requires-Python: >=3.10
Requires-Dist: fastmcp>=0.1.0
Requires-Dist: httpx>=0.24.0
Requires-Dist: pymongo>=4.0.0
